torchdbg/__init__.py
torchdbg-0.3.1.dist-info/METADATA
torchdbg-0.3.1.dist-info/WHEEL
torchdbg-0.3.1.dist-info/RECORD
