Metadata-Version: 2.1
Name: torchdbg
Version: 0.3.1
Summary: PyTorch centric eager mode debugger/tracer
License: BSD-3
Author: Edward Z. Yang
Author-email: ezyang@meta.com
Requires-Python: >=3.8,<4.0
Classifier: License :: Other/Proprietary License
Classifier: Programming Language :: Python :: 3
Classifier: Programming Language :: Python :: 3.8
Classifier: Programming Language :: Python :: 3.9
Classifier: Programming Language :: Python :: 3.10
Classifier: Programming Language :: Python :: 3.11
Classifier: Programming Language :: Python :: 3.12
